rai_perception/NOTICE
rai_perception/__init__.py
rai_perception/agents/__init__.py
rai_perception/agents/base_vision_agent.py
rai_perception/agents/grounded_sam.py
rai_perception/agents/grounding_dino.py
rai_perception/configs/__init__.py
rai_perception/configs/gdino_config.py
rai_perception/configs/seg_config.yml
rai_perception/examples/__init__.py
rai_perception/examples/talker.py
rai_perception/scripts/__init__.py
rai_perception/scripts/run_perception_agents.py
rai_perception/tools/__init__.py
rai_perception/tools/gdino_tools.py
rai_perception/tools/segmentation_tools.py
rai_perception/vision_markup/__init__.py
rai_perception/vision_markup/boxer.py
rai_perception/vision_markup/segmenter.py
rai_perception-0.1.5.dist-info/METADATA
rai_perception-0.1.5.dist-info/WHEEL
rai_perception-0.1.5.dist-info/RECORD
