Metadata-Version: 2.3
Name: rai-perception
Version: 0.1.5
Summary: Package for object detection, segmentation and gripping point detection.
Author: Kajetan Rachwał
Author-email: kajetan.rachwal@robotec.ai
Requires-Python: >=3.8,<4.0
Classifier: Programming Language :: Python :: 3
Classifier: Programming Language :: Python :: 3.8
Classifier: Programming Language :: Python :: 3.9
Classifier: Programming Language :: Python :: 3.10
Classifier: Programming Language :: Python :: 3.11
Classifier: Programming Language :: Python :: 3.12
Classifier: Programming Language :: Python :: 3.13
Requires-Dist: rai-gsam2 (>=1.1.2,<2.0.0)
Requires-Dist: rai_core (>=2.0.0.a2,<3.0.0)
Requires-Dist: rf-groundingdino (>=0.2.0,<0.3.0)
Requires-Dist: torch (>=2.3.1,<3.0.0)
Requires-Dist: torchvision (>=0.18.1,<0.19.0)
